{
  "colors": {
    "profi500": "#ee1b39",
    "profi400": "#fc5368",
    "profi300": "#fba0ab",
    "profi200": "#ffd8dd",
    "profi100": "#fff2f4",
    "green500": "#18d15c",
    "green400": "#6be297",
    "green300": "#a3edbe",
    "green200": "#bff2d2",
    "green100": "#e3f9eb",
    "blue500": "#0075ff",
    "blue400": "#4d97ef",
    "blue300": "#80b8f9",
    "blue200": "#b6d7ff",
    "blue100": "#ecf5ff",
    "yellow500": "#ffa116",
    "yellow400": "#ffc46a",
    "yellow300": "#ffdaa2",
    "yellow200": "#ffe5be",
    "yellow100": "#fff3e3",
    "grey500": "#7e8287",
    "grey400": "#c4c6c8",
    "grey300": "#e8e9ea",
    "grey200": "#f3f3f4",
    "grey100": "#f8f8f8",
    "purple500": "#a748ea",
    "purple400": "#c78bf2",
    "purple300": "#dcb6f7",
    "purple200": "#e7ccfa",
    "purple100": "#f4e9fc",
    "white": "#ffffff",
    "whiteAlpha84": "rgba(255,255,255,0.84)",
    "whiteAlpha72": "rgba(255,255,255,0.72)",
    "whiteAlpha60": "rgba(255,255,255,0.60)",
    "whiteAlpha48": "rgba(255,255,255,0.48)",
    "whiteAlpha40": "rgba(255,255,255,0.40)",
    "whiteAlpha32": "rgba(255,255,255,0.32)",
    "whiteAlpha24": "rgba(255,255,255,0.24)",
    "whiteAlpha12": "rgba(255,255,255,0.12)",
    "whiteAlpha4": "rgba(255,255,255,0.04)",
    "black": "#141c25",
    "blackAlpha84": "rgba(20,28,37,0.84)",
    "blackAlpha72": "rgba(20,28,37,0.72)",
    "blackAlpha60": "rgba(20,28,37,0.60)",
    "blackAlpha48": "rgba(20,28,37,0.48)",
    "blackAlpha40": "rgba(20,28,37,0.40)",
    "blackAlpha32": "rgba(20,28,37,0.32)",
    "blackAlpha24": "rgba(20,28,37,0.24)",
    "blackAlpha12": "rgba(20,28,37,0.12)",
    "blackAlpha4": "rgba(20,28,37,0.04)"
  }
}